isilon/__init__.py
isilon/__main__.py
isilon/_logger.py
isilon/client.py
isilon/creds.py
isilon/exceptions.py
isilon/utils.py
isilon/api/__init__.py
isilon/api/accounts.py
isilon/api/base.py
isilon/api/containers.py
isilon/api/discoverability.py
isilon/api/endpoints.py
isilon/api/metadata.py
isilon/api/objects.py
isilon/commands/__init__.py
isilon/commands/accounts.py
isilon/commands/containers.py
isilon/commands/discoverability.py
isilon/commands/endpoints.py
isilon/commands/exec.py
isilon/commands/objects.py
tests/__init__.py
tests/conftest.py
tests/unit/__init__.py
tests/unit/test_base.py
tests/unit/test_credentials.py
tests/unit/test_utils.py
tests/unit/api/__init__.py
tests/unit/api/test_accounts.py
tests/unit/api/test_containers.py
tests/unit/api/test_discoverability.py
tests/unit/api/test_endpoints.py
tests/unit/api/test_objects.py
tests/unit/commands/__init__.py
tests/unit/commands/test_accounts.py
tests/unit/commands/test_containers.py
tests/unit/commands/test_discoverability.py
tests/unit/commands/test_endpoints.py
tests/unit/commands/test_objects.py
isilon_client-0.2.0.dist-info/LICENSE
isilon_client-0.2.0.dist-info/METADATA
isilon_client-0.2.0.dist-info/WHEEL
isilon_client-0.2.0.dist-info/top_level.txt
isilon_client-0.2.0.dist-info/RECORD
