Metadata-Version: 2.1
Name: isilon-client
Version: 0.2.0
Summary: async rest client for isilon object storage
Home-page: https://github.com/amenezes/isilon-client
Author: Alexandre Menezes
Author-email: alexandre.fmenezes@gmail.com
License: Apache-2.0
Project-URL: Documentation, https://isilon-client.amenezes.net
Project-URL: Code, https://github.com/amenezes/isilon-client
Project-URL: Issue tracker, https://github.com/amenezes/isilon-client/issues
Project-URL: Changes, https://github.com/amenezes/isilon-client/releases
Keywords: "asyncio","object-storage"
Platform: UNKNOWN
Classifier: Development Status :: 5 - Production/Stable
Classifier: Framework :: AsyncIO
Classifier: Intended Audience :: Developers
Classifier: License :: OSI Approved :: Apache Software License
Classifier: Operating System :: OS Independent
Classifier: Programming Language :: Python :: 3 :: Only
Classifier: Programming Language :: Python :: 3.8
Classifier: Programming Language :: Python :: 3.9
Classifier: Programming Language :: Python :: 3.10
Classifier: Programming Language :: Python :: Implementation :: CPython
Classifier: Programming Language :: Python :: Implementation :: PyPy
Classifier: Topic :: Software Development :: Libraries
Requires-Python: >=3.6
License-File: LICENSE
Requires-Dist: aiohttp (>=3.5.2)
Requires-Dist: attrs (>=21.3.0)
Provides-Extra: all
Requires-Dist: portray ; extra == 'all'
Requires-Dist: cleo ; extra == 'all'
Provides-Extra: cli
Requires-Dist: cleo ; extra == 'cli'
Provides-Extra: docs
Requires-Dist: portray ; extra == 'docs'
